Metadata-Version: 1.1
Name: django-flashbriefing
Version: 1.0.1
Summary: Amazon Alexa Flash Briefings for Django
Home-page: https://github.com/istrategylabs/django-flashbriefing
Author: ISL
Author-email: dev@isl.co
License: BSD
Platform: any
Classifier: Development Status :: 4 - Beta
Classifier: Environment :: Web Environment
Classifier: Framework :: Django
Classifier: Intended Audience :: Developers
Classifier: Operating System :: OS Independent
Classifier: Programming Language :: Python
Classifier: Programming Language :: Python :: 3.5
Classifier: Programming Language :: Python :: 3.6
Classifier: Topic :: Software Development :: Libraries :: Python Modules
